Workbook

Sheet Main
B3: CEO | C3: Gary Dickerson | E3: Press | J3: P | K3: 230.29
B4: CFO | C4: Brice Hill | E4: Q425 | J4: S | K4: 798 | L4: Q425
J5: MC | K5: =+K3*K4 -> 183771.42
C6: Strengths | J6: C | K6: =+Model!J78 -> 10844 | L6: =+L4 -> Q425
C7: Broad portfolio (diversed biz): deposition, CMP, etching, wiring, etc) EVERY fab needs amat | J7: D | K7: =100+6455 -> 6555 | L7: =+L6 -> Q425
C8: Deep integration with cutting edge noes (2nm, 3nm, 5nm) | J8: EV | K8: =+K5-K6+K7 -> 179482.42
C9: Recurring revenue: once a fab installs a machine, the never remove them, pay for maintenance/upgrades
C11: Weaknesses
C12: Cyclical buisness - tied to semi capex ( TSMC, Samsung, INTC cut spending --> revenue down)
C13: China exposure - Export control risk
C14: Competitive landscape: Lam research (etch & deposition), Toykyo electron (etch & depositin), ASML (EUV reduces deposition steps?)
C16: AMAT sells machines that physically "build" the chip layer by layer
C17: Tools
C18: lay down metals
C19: coat the wafer
C20: carve parts out
C21: fill trenches with wires
C22: place insulators
... C45: Fluorine (F), Chlorine (CI): for etching and cleaning inside AMAT toold

Sheet Model
AB1: 1 | AC1: =+AB1+1 -> 2 | AD1: =+AC1+1 -> 3 | AE1: =+AD1+1 -> 4 | AF1: =+AE1+1 -> 5 | AG1: =+AF1+1 -> 6 | AH1: =+AG1+1 -> 7 | AI1: =+AH1+1 -> 8 | AJ1: =+AI1+1 -> 9 | ... HS1: =+HR1+1 -> 200
F2: 45592 | G2: 45683 | H2: 45774 | I2: 45865 | J2: 45956
C3: Q124 | D3: Q224 | E3: Q324 | F3: Q424 | G3: Q125 | H3: Q225 | I3: Q325 | J3: Q425 | K3: Q126 | L3: Q226 | M3: Q326 | N3: Q426 | Q3: 2015 | R3: =+Q3+1 -> 2016 | S3: =+R3+1 -> 2017 | T3: =+S3+1 -> 2018 | U3: =+T3+1 -> 2019 | V3: =+U3+1 -> 2020 | W3: =+V3+1 -> 2021 | X3: =+W3+1 -> 2022 | Y3: =+X3+1 -> 2023 | ... HS3: =+HR3+1 -> 2225
B4: Samsung | W4: 0.2 | X4: 0.21 | Y4: 0.15 | Z4: 0.12
B5: TSMC | W5: 0.15 | X5: 0.2 | Y5: 0.19 | Z5: 0.11
B6: Intel | X6: 0.1
B8: China | C8: 2997 | D8: 2831 | E8: 2153 | F8: =+Z8-SUM(C8:E8) -> 2136 | G8: 2243 | H8: 1774 | I8: 2548 | J8: 1964 | W8: 7535 | X8: 7254 | Y8: 7247 | Z8: 10117
B9: Korea | C9: 1231 | D9: 988 | E9: 1102 | F9: =+Z9-SUM(C9:E9) -> 1172 | G9: 1667 | H9: 1562 | I9: 1160 | J9: 1219 | W9: 5012 | X9: 4395 | Y9: 4609 | Z9: 4493
B10: taiwan | C10: 559 | D10: 1019 | E10: 1148 | F10: =+Z10-SUM(C10:E10) -> 1284 | G10: 1183 | H10: 1997 | I10: 1843 | J10: 1834 | W10: 4742 | X10: 6262 | Y10: 5670 | Z10: 4010
B11: Japan | C11: 565 | D11: 453 | E11: 555 | F11: =+Z11-SUM(C11:E11) -> 581 | G11: 540 | H11: 572 | I11: 713 | J11: 448 | W11: 1962 | X11: 2012 | Y11: 2075 | Z11: 2154
B12: Southeast Asia | C12: 186 | D12: 213 | E12: 428 | F12: =+Z12-SUM(C12:E12) -> 314 | G12: 283 | H12: 135 | I12: 195 | J12: 460 | W12: 677 | X12: 1084 | Y12: 758 | Z12: 1141
B13: APAC | C13: =+SUM(C8:C12) -> 5538 | D13: =+SUM(D8:D12) -> 5504 | E13: =+SUM(E8:E12) -> 5386 | F13: =+SUM(F8:F12) -> 5487 | G13: =+SUM(G8:G12) -> 5916 | H13: =+SUM(H8:H12) -> 6040 | I13: =+SUM(I8:I12) -> 6459 | J13: =+SUM(J8:J12) -> 5925 | W13: =+SUM(W8:W12) -> 19928 | X13: =+SUM(X8:X12) -> 21007 | Y13: =+SUM(Y8:Y12) -> 20359 | Z13: =+SUM(Z8:Z12) -> 21915
B14: US | C14: 759 | D14: 853 | E14: 1053 | F14: =+Z14-SUM(C14:E14) -> 1153 | G14: 917 | H14: 808 | I14: 683 | J14: 655 | W14: 2038 | X14: 3104 | Y14: 4006 | Z14: 3818
B15: Europe | C15: 410 | D15: 289 | E15: 339 | F15: =+Z15-SUM(C15:E15) -> 405 | G15: 330 | H15: 252 | I15: 160 | J15: 220 | W15: 1097 | X15: 1674 | Y15: 2152 | Z15: 1443
B17: Foundry, Logic | C17: 0.62 | D17: 0.65 | E17: 0.72 | F17: 0.73 | G17: 0.68 | H17: 0.65 | I17: 0.69 | J17: 0.65 | W17: 0.6 | X17: 0.66 | Y17: 0.77 | Z17: 0.68 | AA17: 0.67
B18: DRAM | C18: 0.34 | D18: 0.32 | E18: 0.24 | F18: 0.23 | G18: 0.28 | H18: 0.27 | I18: 0.22 | J18: 0.29 | W18: 0.19 | X18: 0.19 | Y18: 0.17 | Z18: 0.28 | AA18: 0.26
B19: Flash (NAND) | C19: 0.04 | D19: 0.03 | E19: 0.04 | F19: 0.04 | G19: 0.04 | H19: 0.08 | I19: 0.09 | J19: 0.06 | W19: 0.21 | X19: 0.15 | Y19: 0.06 | Z19: 0.04 | AA19: 0.07
B21: Semi Systems | C21: 4909 | D21: 4901 | E21: 4924 | F21: =+Z21-SUM(C21:E21) -> 5177 | G21: 5356 | H21: 5255 | I21: 5427 | J21: 4760 | K21: =+K$25* (G21/G$25) -> 5119.8158 | W21: 16286 | X21: 18797 | Y21: 19698 | Z21: 19911 | AA21: =SUM(G21:J21) -> 20798
B22: Applied Global Serv | C22: 1476 | D22: 1530 | E22: 1580 | F22: =+Z22-SUM(C22:E22) -> 1639 | G22: 1594 | H22: 1566 | I22: 1600 | J22: 1625 | K22: =+K$25* (G22/G$25) -> 1523.7092 | W22: 5013 | X22: 5543 | Y22: 5732 | Z22: 6225 | AA22: =SUM(G22:J22) -> 6385
B23: Display | C23: 244 | D23: 179 | E23: 251 | F23: =+Z23-SUM(C23:E23) -> 211 | G23: 183 | H23: 259 | I23: 263 | K23: =+K$25* (G23/G$25) -> 174.93023 | W23: 1634 | X23: 1331 | Y23: 868 | Z23: 885 | AA23: =SUM(G23:J23) -> 705
B24: Corp/Other | C24: 78 | D24: 36 | E24: 23 | F24: =+Z24-SUM(C24:E24) -> 18 | G24: 33 | H24: 20 | I24: 12 | K24: =+K$25* (G24/G$25) -> 31.544795 | W24: 130 | X24: 114 | Y24: 219 | Z24: 155 | AA24: =SUM(G24:J24) -> 65
B25: Net Revenue | C25: 6707 | D25: 6646 | E25: =+SUM(E21:E24) -> 6778 | F25: =+SUM(F21:F24) -> 7045 | G25: 7166 | H25: 7100 | I25: =+SUM(I21:I24) -> 7302 | J25: 6800 | K25: =AVERAGE(6850-500,6850+500) -> 6850 | L25: =+H25*1.03 -> 7313 | M25: =+I25*1.08 -> 7886.16 | N25: =+J25*1.08 -> 7344 | W25: 23063 | X25: 25785 | Y25: 26517 | Z25: 27176 | AA25: =SUM(G25:J25) -> 28368 | AB25: =SUM(K25:N25) -> 29393.16 | AC25: =+AB25*1.04 -> 30568.886 | AD25: =+AC25*1.04 -> 31791.642 | AE25: =+AD25*1.04 -> 33063.308 | AF25: =+AE25*1.04 -> 34385.84 | AG25: =+AF25*1.04 -> 35761.273 | AH25: =+AG25*1.04 -> 37191.724 | AI25: =+AH25*1.04 -> 38679.393 | AJ25: =+AI25*1.04 -> 40226.569
B26: C | C26: 3503 | D26: 3493 | E26: 3573 | F26: =+Z26-SUM(C26:E26) -> 3710 | G26: 3670 | H26: 3615 | I26: 3740 | J26: 3535 | K26: =+K$25*(G26/G$25) -> 3508.1636 | L26: =+L$25*(H26/H$25) -> 3723.45 | M26: =+M$25*(I26/I$25) -> 4039.2 | N26: =+N$25*(J26/J$25) -> 3817.8 | W26: 12149 | X26: 13792 | Y26: 14133 | Z26: 14279 | AA26: =SUM(G26:J26) -> 14560 | AB26: =SUM(K26:N26) -> 15088.614 | AC26: =+AC$25*(AB26/AB$25) -> 15692.158 | AD26: =+AD$25*(AC26/AC$25) -> 16319.844 | AE26: =+AE$25*(AD26/AD$25) -> 16972.638 | AF26: =+AF$25*(AE26/AE$25) -> 17651.544 | AG26: =+AG$25*(AF26/AF$25) -> 18357.605 | AH26: =+AH$25*(AG26/AG$25) -> 19091.91 | AI26: =+AI$25*(AH26/AH$25) -> 19855.586 | AJ26: =+AJ$25*(AI26/AI$25) -> 20649.81
B27: R&D | C27: 754 | D27: 785 | E27: 836 | F27: =+Z27-SUM(C27:E27) -> 858 | G27: 859 | H27: 893 | I27: 901 | J27: 917 | K27: =+K$25*(G27/G$25) -> 821.12057 | L27: =+L$25*(H27/H$25) -> 919.79 | M27: =+M$25*(I27/I$25) -> 973.08 | N27: =+N$25*(J27/J$25) -> 990.36 | W27: 2485 | X27: 2771 | Y27: 3102 | Z27: 3233 | AA27: =SUM(G27:J27) -> 3570 | AB27: =SUM(K27:N27) -> 3704.3506 | AC27: =+AC$25*(AB27/AB$25) -> 3852.5246 | AD27: =+AD$25*(AC27/AC$25) -> 4006.6256 | AE27: =+AE$25*(AD27/AD$25) -> 4166.8906 | AF27: =+AF$25*(AE27/AE$25) -> 4333.5662 | AG27: =+AG$25*(AF27/AF$25) -> 4506.9089 | AH27: =+AH$25*(AG27/AG$25) -> 4687.1852 | AI27: =+AI$25*(AH27/AH$25) -> 4874.6726 | AJ27: =+AJ$25*(AI27/AI$25) -> 5069.6595
B28: M&S | C28: 207 | D28: 209 | E28: 205 | F28: =+Z28-SUM(C28:E28) -> 215 | G28: 206 | H28: 216 | I28: 224 | J28: 212 | K28: =+K$25*(G28/G$25) -> 196.91599 | L28: =+L$25*(H28/H$25) -> 222.48 | M28: =+M$25*(I28/I$25) -> 241.92 | N28: =+N$25*(J28/J$25) -> 228.96 | W28: 609 | X28: 703 | Y28: 776 | Z28: 836 | AA28: =SUM(G28:J28) -> 858 | AB28: =SUM(K28:N28) -> 890.27599 | AC28: =+AC$25*(AB28/AB$25) -> 925.88703 | AD28: =+AD$25*(AC28/AC$25) -> 962.92251 | AE28: =+AE$25*(AD28/AD$25) -> 1001.4394 | AF28: =+AF$25*(AE28/AE$25) -> 1041.497 | AG28: =+AG$25*(AF28/AF$25) -> 1083.1569 | AH28: =+AH$25*(AG28/AG$25) -> 1126.4831 | AI28: =+AI$25*(AH28/AH$25) -> 1171.5425 | AJ28: =+AJ$25*(AI28/AI$25) -> 1218.4042
B29: G&A | C29: 276 | D29: 247 | E29: 222 | F29: =+Z29-SUM(C29:E29) -> 216 | G29: 256 | H29: 207 | I29: 204 | J29: 243 | K29: =+K$25*(G29/G$25) -> 244.71114 | L29: =+L$25*(H29/H$25) -> 213.21 | M29: =+M$25*(I29/I$25) -> 220.32 | N29: =+N$25*(J29/J$25) -> 262.44 | W29: 620 | X29: 735 | Y29: 852 | Z29: 961 | AA29: =SUM(G29:J29) -> 910 | AB29: =SUM(K29:N29) -> 940.68114 | AC29: =+AC$25*(AB29/AB$25) -> 978.30838 | AD29: =+AD$25*(AC29/AC$25) -> 1017.4407 | AE29: =+AE$25*(AD29/AD$25) -> 1058.1383 | AF29: =+AF$25*(AE29/AE$25) -> 1100.4639 | AG29: =+AG$25*(AF29/AF$25) -> 1144.4824 | AH29: =+AH$25*(AG29/AG$25) -> 1190.2617 | AI29: =+AI$25*(AH29/AH$25) -> 1237.8722 | AJ29: =+AJ$25*(AI29/AI$25) -> 1287.3871
B30: Operating Income | C30: =+C25-SUM(C26:C29) -> 1967 | D30: =+D25-SUM(D26:D29) -> 1912 | E30: =+E25-SUM(E26:E29) -> 1942 | F30: =+F25-SUM(F26:F29) -> 2046 | G30: =+G25-SUM(G26:G29) -> 2175 | H30: =+H25-SUM(H26:H29) -> 2169 | I30: =+I25-SUM(I26:I29) -> 2233 | J30: =+J25-SUM(J26:J29) -> 1893 | ... N30: =+N25-SUM(N26:N29) -> 2044.44 | W30: =+W25-SUM(W26:W29) -> 7200 | X30: =+X25-SUM(X26:X29) -> 7784 | Y30: =+Y25-SUM(Y26:Y29) -> 7654 | Z30: =+Z25-SUM(Z26:Z29) -> 7867 | AA30: =SUM(G30:J30) -> 8470 | AB30: =+AB25-SUM(AB26:AB29) -> 8769.2388 | AC30: =+AC25-SUM(AC26:AC29) -> 9120.0083 | AD30: =+AD25-SUM(AD26:AD29) -> 9484.8086 | AE30: =+AE25-SUM(AE26:AE29) -> 9864.201 | AF30: =+AF25-SUM(AF26:AF29) -> 10258.769 | AG30: =+AG25-SUM(AG26:AG29) -> 10669.12 | AH30: =+AH25-SUM(AH26:AH29) -> 11095.885 | AI30: =+AI25-SUM(AI26:AI29) -> 11539.72 | AJ30: =+AJ25-SUM(AJ26:AJ29) -> 12001.309
B31: Interest Exp | C31: 59 | D31: 59 | E31: 63 | F31: =+Z31-SUM(C31:E31) -> 66 | G31: 64 | H31: 68 | I31: 66 | J31: 71 | K31: =AVERAGE(G31:J31) -> 67.25 | L31: =AVERAGE(H31:K31) -> 68.0625 | M31: =AVERAGE(I31:L31) -> 68.078125 | N31: =AVERAGE(J31:M31) -> 68.597656 | W31: 236 | X31: 228 | Y31: 238 | Z31: 247 | AA31: =SUM(G31:J31) -> 269 | AB31: =SUM(K31:N31) -> 271.98828 | AC31: =AVERAGE(Y31:AB31) -> 256.49707 | AD31: =AVERAGE(Z31:AC31) -> 261.12134 | AE31: =AVERAGE(AA31:AD31) -> 264.65167 | AF31: =AVERAGE(AB31:AE31) -> 263.56459 | AG31: =AVERAGE(AC31:AF31) -> 261.45867 | AH31: =AVERAGE(AD31:AG31) -> 262.69907 | AI31: =AVERAGE(AE31:AH31) -> 263.0935 | AJ31: =AVERAGE(AF31:AI31) -> 262.70396
B32: Interest Income | C32: 395 | D32: 141 | E32: 81 | F32: =+Z32-SUM(C32:E32) -> -85 | G32: 8 | H32: 221 | I32: 396 | J32: 626 | K32: =AVERAGE(G32:J32) -> 312.75 | L32: =AVERAGE(H32:K32) -> 388.9375 | M32: =AVERAGE(I32:L32) -> 430.92188 | N32: =AVERAGE(J32:M32) -> 439.65234 | W32: 118 | X32: 39 | Y32: 300 | Z32: 532 | AA32: =SUM(G32:J32) -> 1251 | AB32: =+AA55*$AM$40 -> 128.67 | AC32: =+AB55*$AM$40 -> 385.09704 | AD32: =+AC55*$AM$40 -> 620.6192 | AE32: =+AD55*$AM$40 -> 871.31122 | AF32: =+AE55*$AM$40 -> 1137.9589 | AG32: =+AF55*$AM$40 -> 1421.4725 | AH32: =+AG55*$AM$40 -> 1722.7095 | AI32: =+AH55*$AM$40 -> 2042.454 | AJ32: =+AI55*$AM$40 -> 2381.6335
B33: EBT | C33: =+C30-C31+C32 -> 2303 | D33: =+D30-D31+D32 -> 1994 | E33: =+E30-E31+E32 -> 1960 | F33: =+F30-F31+F32 -> 1895 | G33: =+G30-G31+G32 -> 2119 | H33: =+H30-H31+H32 -> 2322 | I33: =+I30-I31+I32 -> 2563 | J33: =+J30-J31+J32 -> 2448 | ... N33: =+N30-N31+N32 -> 2415.4947 | W33: =+W30-W31+W32 -> 7082 | X33: =+X30-X31+X32 -> 7595 | Y33: =+Y30-Y31+Y32 -> 7716 | Z33: =+Z30-Z31+Z32 -> 8152 | AA33: =SUM(G33:J33) -> 9452 | AB33: =SUM(K33:N33) -> 10069.512 | AC33: =+AC30-AC31+AC32 -> 9248.6083 | AD33: =+AD30-AD31+AD32 -> 9844.3065 | AE33: =+AE30-AE31+AE32 -> 10470.861 | AF33: =+AF30-AF31+AF32 -> 11133.163 | AG33: =+AG30-AG31+AG32 -> 11829.134 | AH33: =+AH30-AH31+AH32 -> 12555.895 | AI33: =+AI30-AI31+AI32 -> 13319.08 | AJ33: =+AJ30-AJ31+AJ32 -> 14120.238
B34: Taxes | C34: 284 | D34: 272 | E34: 255 | F34: =+Z34-SUM(C34:E34) -> 164 | G34: 934 | H34: 185 | I34: 784 | J34: 370 | K34: =+K33*(J34/J33) -> 351.34716 | L34: =+L33*(K34/K33) -> 386.16407 | M34: =+M33*(L34/L33) -> 419.34599 | N34: =+N33*(M34/M33) -> 365.08702 | W34: 883 | X34: 1074 | Y34: 860 | Z34: 975 | AA34: =SUM(G34:J34) -> 2273 | AB34: =SUM(K34:N34) -> 1521.9442 | AC34: =+AC33*(AB34/AB33) -> 1397.8697 | AD34: =+AD33*(AC34/AC33) -> 1487.9058 | AE34: =+AE33*(AD34/AD33) -> 1582.6056 | AF34: =+AF33*(AE34/AE33) -> 1682.7085 | AG34: =+AG33*(AF34/AF33) -> 1787.9001 | AH34: =+AH33*(AG34/AG33) -> 1897.7456 | AI34: =+AI33*(AH34/AH33) -> 2013.0963 | AJ34: =+AJ33*(AI34/AI33) -> 2134.1863
B35: Net Income | C35: =+C33-C34 -> 2019 | D35: =+D33-D34 -> 1722 | E35: =+E33-E34 -> 1705 | F35: =+F33-F34 -> 1731 | G35: =+G33-G34 -> 1185 | H35: =+H33-H34 -> 2137 | I35: =+I33-I34 -> 1779 | J35: =+J33-J34 -> 2078 | ... N35: =+N33-N34 -> 2050.4077 | W35: =+W33-W34 -> 6199 | X35: =+X33-X34 -> 6521 | Y35: =+Y33-Y34 -> 6856 | Z35: =+Z33-Z34 -> 7177 | AA35: =SUM(G35:J35) -> 7179 | AB35: =SUM(K35:N35) -> 8547.5679 | AC35: =+AC33-AC34 -> 7850.7386 | AD35: =+AD33-AD34 -> 8356.4007 | AE35: =+AE33-AE34 -> 8888.255 | AF35: =+AF33-AF34 -> 9450.4548 | AG35: =+AG33-AG34 -> 10041.234 | AH35: =+AH33-AH34 -> 10658.149 | AI35: =+AI33-AI34 -> 11305.984 | AJ35: =+AJ33-AJ34 -> 11986.052 | AK35: =+AJ35*(1+$AM$41) -> 12225.773 | AL35: =+AK35*(1+$AM$41) -> 12470.288 | AM35: =+AL35*(1+$AM$41) -> 12719.694 | AN35: =+AM35*(1+$AM$41) -> 12974.088 | AO35: =+AN35*(1+$AM$41) -> 13233.57 | AP35: =+AO35*(1+$AM$41) -> 13498.241 | AQ35: =+AP35*(1+$AM$41) -> 13768.206 | AR35: =+AQ35*(1+$AM$41) -> 14043.57 | ... HS35: =+HR35*(1+$AM$41) -> 526391.62
B36: Diluted | C36: 237 | D36: 836 | E36: 833 | G36: 819 | H36: 812 | I36: 802 | J36: 798 | K36: =+J36 -> 798 | L36: =+K36 -> 798 | M36: =+L36 -> 798 | N36: =+M36 -> 798 | W36: 968.59375 | X36: 876.47849 | Y36: 845.37608 | Z36: 833.56562 | AA36: =+AA35/AA37 -> 806.54998 | AB36: =+AB35/AB37 -> 798 | AC36: =+AB36 -> 798 | AD36: =+AC36 -> 798 | AE36: =+AD36 -> 798 | AF36: =+AE36 -> 798 | AG36: =+AF36 -> 798 | AH36: =+AG36 -> 798 | AI36: =+AH36 -> 798 | AJ36: =+AI36 -> 798
B37: EPS | C37: =+C35/C36 -> 8.5189873 | D37: =+D35/D36 -> 2.0598086 | E37: =+E35/E36 -> 2.0468187 | F37: =+Z37-SUM(C37:E37) -> -4.0156147 | G37: =+G35/G36 -> 1.4468864 | H37: =+H35/H36 -> 2.6317734 | I37: =+I35/I36 -> 2.2182045 | J37: =+J35/J36 -> 2.60401 | K37: =+K35/K36 -> 2.4727338 | L37: =+L35/L36 -> 2.7177706 | M37: =+M35/M36 -> 2.9513004 | N37: =+N35/N36 -> 2.5694332 | W37: =+W35/W36 -> 6.4 | X37: =+X35/X36 -> 7.44 | Y37: =+Y35/Y36 -> 8.11 | Z37: =+Z35/Z36 -> 8.61 | AA37: =SUM(G37:J37) -> 8.9008744 | AB37: =SUM(K37:N37) -> 10.711238 | AC37: =+AC35/AC36 -> 9.8380182 | AD37: =+AD35/AD36 -> 10.47168 | AE37: =+AE35/AE36 -> 11.138164 | AF37: =+AF35/AF36 -> 11.842675 | AG37: =+AG35/AG36 -> 12.582999 | AH37: =+AH35/AH36 -> 13.356077 | AI37: =+AI35/AI36 -> 14.1679 | AJ37: =+AJ35/AJ36 -> 15.020115
AB38: =+AB35/(1+$AM$42)^AB1 -> 7914.4148 | AC38: =+AC35/(1+$AM$42)^AC1 -> 6730.7429 | AD38: =+AD35/(1+$AM$42)^AD1 -> 6633.5803 | AE38: =+AE35/(1+$AM$42)^AE1 -> 6533.1327 | AF38: =+AF35/(1+$AM$42)^AF1 -> 6431.8207 | AG38: =+AG35/(1+$AM$42)^AG1 -> 6327.6804 | AH38: =+AH35/(1+$AM$42)^AH1 -> 6218.9278 | AI38: =+AI35/(1+$AM$42)^AI1 -> 6108.2714 | ... HS38: =+HS35/(1+$AM$42)^HS1 -> 0.10878221
B39: Growth YY
B40: Net Revenue | G40: =+G25/C25-1 -> 0.068435962 | H40: =+H25/D25-1 -> 0.068311766 | I40: =+I25/E25-1 -> 0.077308941 | J40: =+J25/F25-1 -> -0.034776437 | K40: =+K25/G25-1 -> -0.044097125 | L40: =+L25/H25-1 -> 0.03 | M40: =+M25/I25-1 -> 0.08 | N40: =+N25/J25-1 -> 0.08 | X40: =+X25/W25-1 -> 0.11802454 | Y40: =+Y25/X25-1 -> 0.028388598 | Z40: =+Z25/Y25-1 -> 0.024851982 | AA40: =+AA25/Z25-1 -> 0.043862231 | AB40: =+AB25/AA25-1 -> 0.036137902 | AC40: =+AC25/AB25-1 -> 0.04 | AD40: =+AD25/AC25-1 -> 0.04 | AE40: =+AE25/AD25-1 -> 0.04 | ... AJ40: =+AJ25/AI25-1 -> 0.04 | AL40: ROIC | AM40: 0.03
B41: Semi Systems | G41: =+G21/C21-1 -> 0.091057242 | H41: =+H21/D21-1 -> 0.072230157 | I41: =+I21/E21-1 -> 0.10215272 | J41: =+J21/F21-1 -> -0.08054858 | K41: =+K21/G21-1 -> -0.044097125 | X41: =+X21/W21-1 -> 0.15418151 | Y41: =+Y21/X21-1 -> 0.047933181 | Z41: =+Z21/Y21-1 -> 0.010813281 | AA41: =+AA21/Z21-1 -> 0.04454824 | AL41: Terminal | AM41: 0.02
B42: Applied Global Serv | G42: =+G22/C22-1 -> 0.079945799 | H42: =+H22/D22-1 -> 0.023529412 | I42: =+I22/E22-1 -> 0.012658228 | J42: =+J22/F22-1 -> -0.0085417938 | K42: =+K22/G22-1 -> -0.044097125 | X42: =+X22/W22-1 -> 0.10572511 | Y42: =+Y22/X22-1 -> 0.034097059 | Z42: =+Z22/Y22-1 -> 0.086008374 | AA42: =+AA22/Z22-1 -> 0.025702811 | AL42: Discount | AM42: 0.08
B43: Display | G43: =+G23/C23-1 -> -0.25 | H43: =+H23/D23-1 -> 0.44692737 | I43: =+I23/E23-1 -> 0.047808765 | J43: =+J23/F23-1 -> -1 | K43: =+K23/G23-1 -> -0.044097125 | X43: =+X23/W23-1 -> -0.18543452 | Y43: =+Y23/X23-1 -> -0.34785875 | Z43: =+Z23/Y23-1 -> 0.019585253 | AA43: =+AA23/Z23-1 -> -0.20338983 | AL43: NPV | AM43: =NPV(AM42,AB35:HS35) -> 160824.9
B44: Corp/Other | G44: =+G24/C24-1 -> -0.57692308 | H44: =+H24/D24-1 -> -0.44444444 | I44: =+I24/E24-1 -> -0.47826087 | J44: =+J24/F24-1 -> -1 | K44: =+K24/G24-1 -> -0.044097125 | X44: =+X24/W24-1 -> -0.12307692 | Y44: =+Y24/X24-1 -> 0.92105263 | Z44: =+Z24/Y24-1 -> -0.29223744 | AA44: =+AA24/Z24-1 -> -0.58064516 | AL44: Shares | AM44: =+Main!K4 -> 798
B45: C | G45: =+G26/C26-1 -> 0.047673423 | H45: =+H26/D26-1 -> 0.034926997 | I45: =+I26/E26-1 -> 0.046739435 | J45: =+J26/F26-1 -> -0.047169811 | K45: =+K26/G26-1 -> -0.044097125 | AL45: Estimate | AM45: =+AM43/AM44 -> 201.53497
B46: Margins | AL46: Current | AM46: =+Main!K3 -> 230.29
B47: GM% | C47: =(C25-C26)/C25 -> 0.47770986 | D47: =(D25-D26)/D25 -> 0.4744207 | E47: =(E25-E26)/E25 -> 0.47285335 | F47: =(F25-F26)/F25 -> 0.47338538 | G47: =(G25-G26)/G25 -> 0.48785934 | H47: =(H25-H26)/H25 -> 0.49084507 | I47: =(I25-I26)/I25 -> 0.48781156 | J47: =(J25-J26)/J25 -> 0.48014706 | ... N47: =(N25-N26)/N25 -> 0.48014706 | X47: =(X25-X26)/X25 -> 0.46511538 | Y47: =(Y25-Y26)/Y25 -> 0.46702116 | Z47: =(Z25-Z26)/Z25 -> 0.47457315 | AA47: =(AA25-AA26)/AA25 -> 0.48674563 | AB47: =(AB25-AB26)/AB25 -> 0.48666242 | AC47: =(AC25-AC26)/AC25 -> 0.48666242 | AD47: =(AD25-AD26)/AD25 -> 0.48666242 | AE47: =(AE25-AE26)/AE25 -> 0.48666242 | ... AJ47: =(AJ25-AJ26)/AJ25 -> 0.48666242 | AL47: Upside | AM47: =+AM45/AM46-1 -> -0.12486444
B48: OM% | C48: =+C30/C25 -> 0.29327568 | D48: =+D30/D25 -> 0.28769184 | E48: =+E30/E25 -> 0.2865152 | F48: =+F30/F25 -> 0.29041874 | G48: =+G30/G25 -> 0.30351661 | H48: =+H30/H25 -> 0.30549296 | I48: =+I30/I25 -> 0.30580663 | J48: =+J30/J25 -> 0.27838235 | ... N48: =+N30/N25 -> 0.27838235 | X48: =+X30/X25 -> 0.30188094 | Y48: =+Y30/Y25 -> 0.28864502 | Z48: =+Z30/Z25 -> 0.28948337 | AA48: =+AA30/AA25 -> 0.29857586 | AB48: =+AB30/AB25 -> 0.29834284 | AC48: =+AC30/AC25 -> 0.29834284 | AD48: =+AD30/AD25 -> 0.29834284 | AE48: =+AE30/AE25 -> 0.29834284 | ... AJ48: =+AJ30/AJ25 -> 0.29834284
AL49: EV / FY26E | AM49: =+Main!$K$8 /Model!AB35 -> 20.998069
B50: R&D | C50: =+C27/C$25 -> 0.11241986 | D50: =+D27/D$25 -> 0.11811616 | E50: =+E27/E$25 -> 0.12334022 | F50: =+F27/F$25 -> 0.1217885 | G50: =+G27/G$25 -> 0.11987162 | H50: =+H27/H$25 -> 0.12577465 | I50: =+I27/I$25 -> 0.12339085 | J50: =+J27/J$25 -> 0.13485294 | ... N50: =+N27/N$25 -> 0.13485294 | W50: =+W27/W$25 -> 0.10774834 | X50: =+X27/X$25 -> 0.10746558 | Y50: =+Y27/Y$25 -> 0.11698156 | Z50: =+Z27/Z$25 -> 0.11896526 | AA50: =+AA27/AA$25 -> 0.12584602 | AB50: =+AB27/AB$25 -> 0.12602764 | AC50: =+AC27/AC$25 -> 0.12602764 | AD50: =+AD27/AD$25 -> 0.12602764 | AE50: =+AE27/AE$25 -> 0.12602764 | AL50: EV / FY27E | AM50: =+Main!$K$8 /Model!AC35 -> 22.861852
B51: M&S | C51: =+C28/C$25 -> 0.030863277 | D51: =+D28/D$25 -> 0.031447487 | E51: =+E28/E$25 -> 0.03024491 | F51: =+F28/F$25 -> 0.030518098 | G51: =+G28/G$25 -> 0.02874686 | H51: =+H28/H$25 -> 0.030422535 | I51: =+I28/I$25 -> 0.030676527 | J51: =+J28/J$25 -> 0.031176471 | ... N51: =+N28/N$25 -> 0.031176471 | W51: =+W28/W$25 -> 0.026405932 | X51: =+X28/X$25 -> 0.027263913 | Y51: =+Y28/Y$25 -> 0.029264246 | Z51: =+Z28/Z$25 -> 0.030762437 | AA51: =+AA28/AA$25 -> 0.030245347 | AB51: =+AB28/AB$25 -> 0.030288543 | AC51: =+AC28/AC$25 -> 0.030288543 | AD51: =+AD28/AD$25 -> 0.030288543 | AE51: =+AE28/AE$25 -> 0.030288543
B52: G&A | C52: =+C29/C$25 -> 0.041151036 | D52: =+D29/D$25 -> 0.037165212 | E52: =+E29/E$25 -> 0.032753024 | F52: =+F29/F$25 -> 0.030660043 | G52: =+G29/G$25 -> 0.035724253 | H52: =+H29/H$25 -> 0.02915493 | I52: =+I29/I$25 -> 0.027937551 | J52: =+J29/J$25 -> 0.035735294 | ... N52: =+N29/N$25 -> 0.035735294 | W52: =+W29/W$25 -> 0.026882886 | X52: =+X29/X$25 -> 0.028504945 | Y52: =+Y29/Y$25 -> 0.032130331 | Z52: =+Z29/Z$25 -> 0.035362084 | AA52: =+AA29/AA$25 -> 0.032078398 | AB52: =+AB29/AB$25 -> 0.032003403 | AC52: =+AC29/AC$25 -> 0.032003403 | AD52: =+AD29/AD$25 -> 0.032003403 | AE52: =+AE29/AE$25 -> 0.032003403 | AL52: Analysts
AL53: Cantor Fitzgerald | AM53: 300 | AN53: 45975
AL54: WF | AM54: 255 | AN54: 45975
B55: Net Cash | F55: =+F80 -> 3211 | G55: =+G80 -> 2098 | H55: =+H80 -> 4142 | I55: =+I80 -> 5273 | J55: =+J80 -> 4289 | AA55: =+J55 -> 4289 | AB55: =+AA55+AB35 -> 12836.568 | AC55: =+AB55+AC35 -> 20687.307 | AD55: =+AC55+AD35 -> 29043.707 | AE55: =+AD55+AE35 -> 37931.962 | AF55: =+AE55+AF35 -> 47382.417 | AG55: =+AF55+AG35 -> 57423.65 | AH55: =+AG55+AH35 -> 68081.8 | AI55: =+AH55+AI35 -> 79387.784 | AJ55: =+AI55+AJ35 -> 91373.836 | AL55: Citi | AM55: 250 | AN55: 45975
B56: Cash | F56: 8022 | G56: 6264 | H56: 6169 | I56: 5384 | J56: 7241 | AL56: Craig-Hallum | AM56: 190 | AN56: 45975
B57: Investments | F57: 1449 | G57: 1949 | H57: 578 | I57: 1630 | J57: 1332 | AL57: Needham | AM57: 260 | AN57: 45975
B58: A/R | F58: 5234 | G58: 5998 | H58: 6187 | I58: 5772 | J58: 5185 | AL58: Average | AM58: =AVERAGE(AM53:AM57) -> 251
B59: Inventories | F59: 5421 | G59: 5501 | H59: 5656 | I59: 5807 | J59: 5915 | AL59: Estimate | AM59: =+AM45 -> 201.53497
B60: OCA | F60: 1094 | G60: 982 | H60: 1118 | I60: 1125 | J60: 1208 | AL60: Vs Consc avg | AM60: =+AM59/AM58-1 -> -0.19707184
B61: LT Investments | F61: 2787 | G61: 2686 | H61: 3638 | I61: 4133 | J61: 4327
B62: PPE | F62: 3339 | G62: 3563 | H62: 3832 | I62: 4124 | J62: 4610 | AL62: BVPS | AM62: =+J75/AM44 -> 25.582707
B63: Goodwill | F63: 3732 | G63: 3768 | H63: 3748 | I63: 3748 | J63: 3707
B64: Intangibles | F64: 249 | G64: 237 | H64: 249 | I64: 238 | J64: 226
B65: Deferred Income tx | F65: 3082 | G65: 2390 | H65: 2457 | I65: 2250 | J65: 2548
B66: Total Assets | F66: =SUM(F56:F65) -> 34409 | G66: =SUM(G56:G65) -> 33338 | H66: =SUM(H56:H65) -> 33632 | I66: =SUM(I56:I65) -> 34211 | J66: =SUM(J56:J65) -> 36299
B68: Debt | F68: 799 | G68: 799 | H68: 799 | I68: 799 | J68: 100
B69: A/P | F69: 4820 | G69: 4485 | H69: 4706 | I69: 4614 | J69: 5333
B70: Contract Liab | F70: 2849 | G70: 2452 | H70: 2491 | I70: 2470 | J70: 2566
B71: LTD | F71: 5460 | G71: 7736 | H71: 5462 | I71: 5463 | J71: 6455
B72: Income Tx Payable | F72: 670 | G72: 684 | H72: 321 | I72: 330 | J72: 356
B73: OL | F73: 810 | G73: 832 | H73: 892 | I73: 1031 | J73: 1074
B74: TL | F74: =SUM(F68:F73) -> 15408 | G74: =SUM(G68:G73) -> 16988 | H74: =SUM(H68:H73) -> 14671 | I74: =SUM(I68:I73) -> 14707 | J74: =SUM(J68:J73) -> 15884
B75: E | F75: 19001 | G75: 18625 | H75: 18961 | I75: 19504 | J75: 20415
B76: TL + E | F76: =+SUM(F74:F75) -> 34409 | G76: =+SUM(G74:G75) -> 35613 | H76: =+SUM(H74:H75) -> 33632 | I76: =+SUM(I74:I75) -> 34211 | J76: =+SUM(J74:J75) -> 36299
B78: Total Cash | C78: =+SUM(C57:C58,C61) -> 0 | D78: =+SUM(D57:D58,D61) -> 0 | E78: =+SUM(E57:E58,E61) -> 0 | F78: =+SUM(F57:F58,F61) -> 9470 | G78: =+SUM(G57:G58,G61) -> 10633 | H78: =+SUM(H57:H58,H61) -> 10403 | I78: =+SUM(I57:I58,I61) -> 11535 | J78: =+SUM(J57:J58,J61) -> 10844
B79: Total Debt | C79: =SUM(C68,C71) -> 0 | D79: =SUM(D68,D71) -> 0 | E79: =SUM(E68,E71) -> 0 | F79: =SUM(F68,F71) -> 6259 | G79: =SUM(G68,G71) -> 8535 | H79: =SUM(H68,H71) -> 6261 | I79: =SUM(I68,I71) -> 6262 | J79: =SUM(J68,J71) -> 6555
B80: Net Cash | C80: =+C78-C79 -> 0 | D80: =+D78-D79 -> 0 | E80: =+E78-E79 -> 0 | F80: =+F78-F79 -> 3211 | G80: =+G78-G79 -> 2098 | H80: =+H78-H79 -> 4142 | I80: =+I78-I79 -> 5273 | J80: =+J78-J79 -> 4289
B81: Book Value | C81: =+C75 -> 0 | D81: =+D75 -> 0 | E81: =+E75 -> 0 | F81: =+F75 -> 19001 | G81: =+G75 -> 18625 | H81: =+H75 -> 18961 | I81: =+I75 -> 19504 | J81: =+J75 -> 20415
B82: Tangible Book Value | C82: =+C75-SUM(C63:C64) -> 0 | D82: =+D75-SUM(D63:D64) -> 0 | E82: =+E75-SUM(E63:E64) -> 0 | F82: =+F75-SUM(F63:F64) -> 15020 | G82: =+G75-SUM(G63:G64) -> 14620 | H82: =+H75-SUM(H63:H64) -> 14964 | I82: =+I75-SUM(I63:I64) -> 15518 | J82: =+J75-SUM(J63:J64) -> 16482
B83: ROTB | C83: =IFERROR(SUM(#REF!)/C82, "") | D83: =IFERROR(SUM(A35:D35)/D82, "") | E83: =IFERROR(SUM(B35:E35)/E82, "") | F83: =IFERROR(SUM(C35:F35)/F82, "") -> 0.47782956 | G83: =IFERROR(SUM(D35:G35)/G82, "") -> 0.43385773 | H83: =IFERROR(SUM(E35:H35)/H82, "") -> 0.45161721 | I83: =IFERROR(SUM(F35:I35)/I82, "") -> 0.44026292 | J83: =IFERROR(SUM(G35:J35)/J82, "") -> 0.43556607
B84: Liquidity & Working Capital
B85: Current Ratio | C85: =IFERROR(SUM(C56:C60)/SUM(C68:C70),"") | D85: =IFERROR(SUM(D56:D60)/SUM(D68:D70),"") | E85: =IFERROR(SUM(E56:E60)/SUM(E68:E70),"") | F85: =IFERROR(SUM(F56:F60)/SUM(F68:F70),"") -> 2.5059046 | G85: =IFERROR(SUM(G56:G60)/SUM(G68:G70),"") -> 2.6750259 | H85: =IFERROR(SUM(H56:H60)/SUM(H68:H70),"") -> 2.4647324 | I85: =IFERROR(SUM(I56:I60)/SUM(I68:I70),"") -> 2.501332 | J85: =IFERROR(SUM(J56:J60)/SUM(J68:J70),"") -> 2.6104513
B86: Quick Ratio | F86: =SUM(F56:F58,F59) / SUM(F68:F70) -> 2.3767123 | G86: =SUM(G56:G58,G59) / SUM(G68:G70) -> 2.5480869 | H86: =SUM(H56:H58,H59) / SUM(H68:H70) -> 2.3249125 | I86: =SUM(I56:I58,I59) / SUM(I68:I70) -> 2.3586198 | J86: =SUM(J56:J58,J59) / SUM(J68:J70) -> 2.4594324
B87: Inventory Turnover | G87: =SUM(D26:G26)/AVERAGE(F59:G59) -> 2.6453031 | H87: =SUM(E26:H26)/AVERAGE(G59:H59) -> 2.6114547 | I87: =SUM(F26:I26)/AVERAGE(H59:I59) -> 2.5708802 | J87: =SUM(G26:J26)/AVERAGE(I59:J59) -> 2.4842177
B88: Days Inv Out | G88: =365/G87 -> 137.98041 | H88: =365/H87 -> 139.76884 | I88: =365/I87 -> 141.97472 | J88: =365/J87 -> 146.92754
B89: Cap Structure
B90: D/E | F90: =+F79/F75 -> 0.32940372 | G90: =+G79/G75 -> 0.45825503 | H90: =+H79/H75 -> 0.3302041 | I90: =+I79/I75 -> 0.32106235 | J90: =+J79/J75 -> 0.32108744
B91: Debt To TangibleEQ | F91: =+F79 / F82 -> 0.41671105 | G91: =+G79 / G82 -> 0.58378933 | H91: =+H79 / H82 -> 0.41840417 | I91: =+I79 / I82 -> 0.40353138 | J91: =+J79 / J82 -> 0.39770659
B92: Capex / Revenue | H92: =ABS(SUM(E106:H106)) / SUM(E25:H25) -> 0.056783794 | I92: =ABS(SUM(F106:I106)) / SUM(F25:I25) -> 0.065774298 | J92: =ABS(SUM(G106:J106)) / SUM(G25:J25) -> 0.079667231
B96: Net Income | E96: 1705 | F96: 1731 | G96: 1185 | H96: 2137 | I96: 1779 | J96: 1897
B97: D&A | E97: 95 | F97: 110 | G97: 105 | H97: 103 | I97: 113 | J97: 114
B98: Restructuring | E98: 0 | F98: 0 | G98: 0 | H98: 0 | I98: 0 | J98: 179
B99: Deferred i/t | E99: -179 | F99: -248 | G99: 668 | H99: 4 | I99: 280 | J99: -313
B100: Investment Impairments | E100: 0 | F100: 241 | G100: 0 | H100: 0 | I100: 0 | J100: -522
B101: SBC | E101: 132 | F101: 141 | G101: 195 | H101: 159 | I101: 158 | J101: 156
B102: Other | E102: 48 | F102: 5 | G102: 95 | H102: -109 | I102: -284 | J102: 59
B103: Change in op asset/liab | E103: 584 | F103: 595 | G103: -1323 | H103: -723 | I103: 588 | J103: 1258
B104: CFFO | C104: =+SUM(C96:C103) -> 0 | D104: =+SUM(D96:D103) -> 0 | E104: =+SUM(E96:E103) -> 2385 | F104: =+SUM(F96:F103) -> 2575 | G104: =+SUM(G96:G103) -> 925 | H104: =+SUM(H96:H103) -> 1571 | I104: =+SUM(I96:I103) -> 2634 | J104: =+SUM(J96:J103) -> 2828
B106: Capex | E106: -297 | F106: -407 | G106: -381 | H106: -510 | I106: -584 | J106: -785
B107: Cash paid for acq | E107: 0 | F107: 0 | G107: -28 | H107: -1 | I107: 0 | J107: 0
B108: Proceeds from asset sale | E108: 0 | F108: 0 | G108: 0 | H108: 33 | I108: 0 | J108: 0
B109: Proceeds from sales of inv | E109: 382 | F109: 956 | G109: 1223 | H109: 1921 | I109: 793 | J109: 1591
...
